general/__init__.py
general/constants.py
playground/__init__.py
playground/test_play.py
rest_api/__init__.py
rest_api/request_actions.py
rest_api/utilities.py
selenium_base/__init__.py
selenium_base/selenium_actions.py
selenium_base/selenium_config.py
selenium_base/selenium_storage.py
shared/__init__.py
shared/db_mysql_capabilities.py
shared/run_parallel.py
shared/shared_utilities.py
unit_tests/__init__.py
unit_tests/actions_unit_test.py
unit_tests/api_unit_test.py
unit_tests/selenium_driver_unit_test.py
seebotesttrix-0.0.2.dist-info/LICENCE
seebotesttrix-0.0.2.dist-info/METADATA
seebotesttrix-0.0.2.dist-info/WHEEL
seebotesttrix-0.0.2.dist-info/top_level.txt
seebotesttrix-0.0.2.dist-info/RECORD
