Metadata-Version: 2.1
Name: seebotesttrix
Version: 0.0.2
Summary: Qualitest package automation infrastructure kit tools for GUI and API tests
Home-page: https://upload.pypi.org/legacy/
Author: Yossi Arar & Moshe Sar Idan
License: MIT
Platform: UNKNOWN
Classifier: Programming Language :: Python :: 3
Classifier: License :: OSI Approved :: MIT License
Classifier: Operating System :: OS Independent
Requires-Python: >=3.7
License-File: LICENCE
Requires-Dist: allure-pytest (==2.9.43)
Requires-Dist: allure-python-commons (==2.9.43)
Requires-Dist: appdirs (==1.4.4)
Requires-Dist: atomicwrites (==1.4.0)
Requires-Dist: attrs (==21.2.0)
Requires-Dist: build (==0.5.1)
Requires-Dist: certifi (==2021.5.30)
Requires-Dist: cffi (==1.14.6)
Requires-Dist: chardet (==4.0.0)
Requires-Dist: colorama (==0.4.4)
Requires-Dist: cryptography (==3.4.7)
Requires-Dist: dnspython (==1.16.0)
Requires-Dist: idna (==2.10)
Requires-Dist: importlib-metadata (==4.6.1)
Requires-Dist: iniconfig (==1.1.1)
Requires-Dist: isodate (==0.6.0)
Requires-Dist: lxml (==4.6.3)
Requires-Dist: msal (==1.9.0)
Requires-Dist: msal-extensions (==0.3.0)
Requires-Dist: msrest (==0.6.21)
Requires-Dist: numpy (==1.21.0)
Requires-Dist: oauthlib (==3.1.1)
Requires-Dist: packaging (==21.0)
Requires-Dist: pandas (==1.3.0)
Requires-Dist: pep517 (==0.10.0)
Requires-Dist: pluggy (==0.13.1)
Requires-Dist: portalocker (==1.7.1)
Requires-Dist: py (==1.10.0)
Requires-Dist: pycparser (==2.20)
Requires-Dist: PyJWT (==2.1.0)
Requires-Dist: pyparsing (==2.4.7)
Requires-Dist: python-dateutil (==2.8.1)
Requires-Dist: python-snappy (==0.6.0)
Requires-Dist: pytz (==2021.1)
Requires-Dist: requests (==2.25.1)
Requires-Dist: requests-oauthlib (==1.3.0)
Requires-Dist: selenium (==3.141.0)
Requires-Dist: six (==1.16.0)
Requires-Dist: soupsieve (==2.2.1)
Requires-Dist: toml (==0.10.2)
Requires-Dist: tqdm (==4.61.2)
Requires-Dist: typing-extensions (==3.10.0.0)
Requires-Dist: urllib3 (==1.26.6)
Requires-Dist: webdrivermanager (==0.10.0)
Requires-Dist: zipp (==3.5.0)
